ex_fuzzy/__init__.py
ex_fuzzy/centroid.py
ex_fuzzy/classifiers.py
ex_fuzzy/cognitive_maps.py
ex_fuzzy/eval_rules.py
ex_fuzzy/eval_tools.py
ex_fuzzy/evolutionary_fit.py
ex_fuzzy/fuzzy_sets.py
ex_fuzzy/maintenance.py
ex_fuzzy/pattern_stability.py
ex_fuzzy/persistence.py
ex_fuzzy/rule_mining.py
ex_fuzzy/rules.py
ex_fuzzy/temporal.py
ex_fuzzy/utils.py
ex_fuzzy/vis_rules.py
ex_fuzzy-1.3.0.dist-info/LICENSE
ex_fuzzy-1.3.0.dist-info/METADATA
ex_fuzzy-1.3.0.dist-info/WHEEL
ex_fuzzy-1.3.0.dist-info/top_level.txt
ex_fuzzy-1.3.0.dist-info/RECORD
