Metadata-Version: 2.1
Name: ex_fuzzy
Version: 1.3.0
Summary: Library to perform explainable AI using fuzzy logic.
Home-page: https://github.com/Fuminides/ex-fuzzy
Download-URL: https://pypi.org/project/ex-fuzzy/
Maintainer: Javier Fumanal Idocin
Maintainer-email: javierfumanalidocin@gmail.com
License: GPL-3.0
Classifier: Development Status :: 4 - Beta
Classifier: Intended Audience :: Science/Research
Classifier: License :: OSI Approved :: GNU General Public License v3 (GPLv3)
Classifier: Programming Language :: Python
Classifier: Programming Language :: Python :: 3.7
Classifier: Topic :: Scientific/Engineering
Classifier: Topic :: Scientific/Engineering :: Artificial Intelligence
Classifier: Topic :: Software Development :: Libraries
Classifier: Topic :: Software Development :: Libraries :: Python Modules
License-File: LICENSE
Requires-Dist: numpy
Requires-Dist: networkx
Requires-Dist: matplotlib
Requires-Dist: pymoo
Requires-Dist: pandas
Requires-Dist: scikit-learn
